{"v":"5.7.14","fr":60,"ip":0,"op":165,"w":430,"h":430,"nm":"Final EXPORT 2","ddd":0,"assets":[{"id":"comp_0","nm":"Final EXPORT","layers":[{"ddd":0,"ind":1,"ty":4,"nm":"Sparkles","sr":1,"ks":{"o":{"a":0,"k":100,"ix":11},"r":{"a":0,"k":31.075,"ix":10},"p":{"a":0,"k":[482.429,256.246,0],"ix":2,"l":2},"a":{"a":0,"k":[601.479,386.81,0],"ix":1,"l":2},"s":{"a":0,"k":[123,123,100],"ix":6,"l":2}},"ao":0,"shapes":[{"ty":"gr","it":[{"ty":"gr","it":[{"ind":0,"ty":"sh","ix":1,"ks":{"a":0,"k":{"i":[[-5.181,-1.331],[0,-1.623],[1.571,-0.404],[4.559,-1.171],[1.313,-5.114],[1.331,-5.181],[1.623,0],[0.404,1.571],[1.171,4.559],[5.114,1.313],[5.181,1.331],[0,1.623],[-1.571,0.404],[-4.559,1.171],[-1.313,5.114],[-1.331,5.181],[-1.623,0],[-0.404,-1.571],[-1.171,-4.559],[-5.114,-1.313]],"o":[[1.571,0.404],[0,1.623],[-5.181,1.331],[-5.114,1.313],[-1.171,4.559],[-0.404,1.571],[-1.623,0],[-1.331,-5.181],[-1.313,-5.114],[-4.559,-1.171],[-1.571,-0.404],[0,-1.623],[5.181,-1.331],[5.114,-1.313],[1.171,-4.559],[0.404,-1.571],[1.623,0],[1.331,5.181],[1.313,5.114],[4.559,1.171]],"v":[[33.352,-3.443],[36.022,0],[33.352,3.443],[17.847,7.426],[7.426,17.847],[3.443,33.352],[0,36.022],[-3.443,33.352],[-7.426,17.847],[-17.847,7.426],[-33.352,3.443],[-36.022,0],[-33.352,-3.443],[-17.847,-7.426],[-7.426,-17.847],[-3.443,-33.352],[0,-36.022],[3.443,-33.352],[7.426,-17.847],[17.847,-7.426]],"c":true},"ix":2},"nm":"Path 1","mn":"ADBE Vector Shape - Group","hd":false},{"ty":"fl","c":{"a":0,"k":[1,1,1,1],"ix":4},"o":{"a":0,"k":100,"ix":5},"r":1,"bm":0,"nm":"Fill 1","mn":"ADBE Vector Graphic - Fill","hd":false},{"ty":"tr","p":{"a":0,"k":[59.491,62.796],"ix":2},"a":{"a":0,"k":[0,0],"ix":1},"s":{"a":0,"k":[100,100],"ix":3},"r":{"a":0,"k":0,"ix":6},"o":{"a":0,"k":100,"ix":7},"sk":{"a":0,"k":0,"ix":4},"sa":{"a":0,"k":0,"ix":5},"nm":"Transform"}],"nm":"Group 1","np":2,"cix":2,"bm":0,"ix":1,"mn":"ADBE Vector Group","hd":false},{"ty":"tr","p":{"a":1,"k":[{"i":{"x":0,"y":1},"o":{"x":0.167,"y":0.255},"t":-96,"s":[540,384],"to":[0,0],"ti":[-25.961,-65.829]},{"t":-46,"s":[744.1,412.487]}],"ix":2},"a":{"a":0,"k":[36.5,36.5],"ix":1},"s":{"a":1,"k":[{"i":{"x":[0.014,0.014],"y":[0.855,0.855]},"o":{"x":[0.18,0.18],"y":[0.388,0.388]},"t":-96,"s":[-14.25,14.25]},{"t":-46,"s":[-41.843,41.843]}],"ix":3},"r":{"a":1,"k":[{"i":{"x":[0],"y":[1]},"o":{"x":[0.167],"y":[0.167]},"t":-96,"s":[-114.293]},{"t":-46,"s":[-282.293]}],"ix":6},"o":{"a":1,"k":[{"i":{"x":[0.833],"y":[0.833]},"o":{"x":[0.167],"y":[0.167]},"t":-64,"s":[100]},{"t":-50,"s":[0]}],"ix":7},"sk":{"a":0,"k":0,"ix":4},"sa":{"a":0,"k":0,"ix":5},"nm":"Transform"}],"nm":"confetti star Outlines 5","np":1,"cix":2,"bm":0,"ix":1,"mn":"ADBE Vector Group","hd":false},{"ty":"gr","it":[{"ty":"gr","it":[{"ind":0,"ty":"sh","ix":1,"ks":{"a":0,"k":{"i":[[-5.181,-1.331],[0,-1.623],[1.571,-0.404],[4.559,-1.171],[1.313,-5.114],[1.331,-5.181],[1.623,0],[0.404,1.571],[1.171,4.559],[5.114,1.313],[5.181,1.331],[0,1.623],[-1.571,0.404],[-4.559,1.171],[-1.313,5.114],[-1.331,5.181],[-1.623,0],[-0.404,-1.571],[-1.171,-4.559],[-5.114,-1.313]],"o":[[1.571,0.404],[0,1.623],[-5.181,1.331],[-5.114,1.313],[-1.171,4.559],[-0.404,1.571],[-1.623,0],[-1.331,-5.181],[-1.313,-5.114],[-4.559,-1.171],[-1.571,-0.404],[0,-1.623],[5.181,-1.331],[5.114,-1.313],[1.171,-4.559],[0.404,-1.571],[1.623,0],[1.331,5.181],[1.313,5.114],[4.559,1.171]],"v":[[33.352,-3.443],[36.022,0],[33.352,3.443],[17.847,7.426],[7.426,17.847],[3.443,33.352],[0,36.022],[-3.443,33.352],[-7.426,17.847],[-17.847,7.426],[-33.352,3.443],[-36.022,0],[-33.352,-3.443],[-17.847,-7.426],[-7.426,-17.847],[-3.443,-33.352],[0,-36.022],[3.443,-33.352],[7.426,-17.847],[17.847,-7.426]],"c":true},"ix":2},"nm":"Path 1","mn":"ADBE Vector Shape - Group","hd":false},{"ty":"fl","c":{"a":0,"k":[1,1,1,1],"ix":4},"o":{"a":0,"k":100,"ix":5},"r":1,"bm":0,"nm":"Fill 1","mn":"ADBE Vector Graphic - Fill","hd":false},{"ty":"tr","p":{"a":0,"k":[36.022,36.978],"ix":2},"a":{"a":0,"k":[0,0],"ix":1},"s":{"a":0,"k":[100,100],"ix":3},"r":{"a":0,"k":0,"ix":6},"o":{"a":0,"k":100,"ix":7},"sk":{"a":0,"k":0,"ix":4},"sa":{"a":0,"k":0,"ix":5},"nm":"Transform"}],"nm":"Group 1","np":2,"cix":2,"bm":0,"ix":1,"mn":"ADBE Vector Group","hd":false},{"ty":"tr","p":{"a":1,"k":[{"i":{"x":0,"y":1},"o":{"x":0.167,"y":0.222},"t":-100,"s":[540,384],"to":[0,0],"ti":[-124,6]},{"t":-50,"s":[722,288]}],"ix":2},"a":{"a":0,"k":[36.5,36.5],"ix":1},"s":{"a":1,"k":[{"i":{"x":[0,0],"y":[1,1]},"o":{"x":[0.167,0.167],"y":[0.167,0.167]},"t":-100,"s":[25,25]},{"t":-50,"s":[73,73]}],"ix":3},"r":{"a":1,"k":[{"i":{"x":[0],"y":[1]},"o":{"x":[0.167],"y":[0.167]},"t":-100,"s":[0]},{"t":-50,"s":[168]}],"ix":6},"o":{"a":1,"k":[{"i":{"x":[0.833],"y":[0.833]},"o":{"x":[0.167],"y":[0.167]},"t":-68,"s":[100]},{"t":-54,"s":[0]}],"ix":7},"sk":{"a":0,"k":0,"ix":4},"sa":{"a":0,"k":0,"ix":5},"nm":"Transform"}],"nm":"confetti star Outlines 4","np":1,"cix":2,"bm":0,"ix":2,"mn":"ADBE Vector Group","hd":false}],"ip":0,"op":165,"st":-132,"bm":0},{"ddd":0,"ind":2,"ty":0,"nm":"Success State Animation 2","refId":"comp_1","sr":1,"ks":{"o":{"a":0,"k":100,"ix":11},"r":{"a":0,"k":0,"ix":10},"p":{"a":0,"k":[471.5,215,0],"ix":2,"l":2},"a":{"a":0,"k":[774.5,396.5,0],"ix":1,"l":2},"s":{"a":0,"k":[66,66,100],"ix":6,"l":2}},"ao":0,"w":1549,"h":793,"ip":0,"op":165,"st":-3,"bm":0}]},{"id":"comp_1","nm":"Success State Animation 2","layers":[{"ddd":0,"ind":1,"ty":0,"nm":"Jumpy Tick 2","refId":"comp_2","sr":0.89999997615814,"ks":{"o":{"a":0,"k":100,"ix":11},"r":{"a":0,"k":0,"ix":10},"p":{"a":0,"k":[774,402.5,0],"ix":2,"l":2},"a":{"a":0,"k":[1258,965,0],"ix":1,"l":2},"s":{"a":0,"k":[100,100,100],"ix":6,"l":2}},"ao":0,"w":2516,"h":1930,"ip":-1.60000038146973,"op":171.99960899353,"st":-16,"bm":0},{"ddd":0,"ind":2,"ty":4,"nm":"Shape Layer 5","sr":1,"ks":{"o":{"a":1,"k":[{"i":{"x":[0.833],"y":[1]},"o":{"x":[0.167],"y":[0]},"t":60,"s":[25]},{"i":{"x":[0.833],"y":[0.833]},"o":{"x":[0.167],"y":[0.167]},"t":76,"s":[25]},{"t":98,"s":[0]}],"ix":11},"r":{"a":0,"k":0,"ix":10},"p":{"a":1,"k":[{"i":{"x":0.833,"y":1},"o":{"x":0.53,"y":0},"t":60,"s":[774.5,412,0],"to":[0,-1.333,0],"ti":[0,1.333,0]},{"t":76,"s":[774.5,404,0]}],"ix":2,"l":2},"a":{"a":0,"k":[0,0,0],"ix":1,"l":2},"s":{"a":1,"k":[{"i":{"x":[0.18,0.18,0.18],"y":[1,1,1]},"o":{"x":[0.167,0.167,0.167],"y":[0.167,0.167,0]},"t":60,"s":[527,527,100]},{"t":104,"s":[865,865,100]}],"ix":6,"l":2}},"ao":0,"shapes":[{"d":3,"ty":"el","s":{"a":0,"k":[71,71],"ix":2},"p":{"a":0,"k":[0,0],"ix":3},"nm":"Ellipse Path 1","mn":"ADBE Vector Shape - Ellipse","hd":false},{"ty":"fl","c":{"a":0,"k":[1,1,1,1],"ix":4},"o":{"a":0,"k":100,"ix":5},"r":2,"bm":0,"nm":"Fill 1","mn":"ADBE Vector Graphic - Fill","hd":false}],"ip":60,"op":130,"st":-276,"bm":0}]},{"id":"comp_2","nm":"Jumpy Tick 2","layers":[{"ddd":0,"ind":1,"ty":4,"nm":"tick Outlines 2","sr":1,"ks":{"o":{"a":0,"k":100,"ix":11},"r":{"a":0,"k":0,"ix":10},"p":{"a":0,"k":[1188.865,976.622,0],"ix":2,"l":2},"a":{"a":0,"k":[18.976,67.018,0],"ix":1,"l":2},"s":{"a":0,"k":[121,121,100],"ix":6,"l":2}},"ao":0,"shapes":[{"ty":"gr","it":[{"ind":0,"ty":"sh","ix":1,"ks":{"a":1,"k":[{"i":{"x":0.833,"y":0.833},"o":{"x":0.167,"y":0.167},"t":0,"s":[{"i":[[0,0],[0,0],[0,0]],"o":[[0,0],[0,0],[0,0]],"v":[[-53.125,9.625],[-20.5,40.625],[53.125,-40.625]],"c":false}]},{"t":239,"s":[{"i":[[0,0],[0,0],[0,0]],"o":[[0,0],[0,0],[0,0]],"v":[[-53.125,9.625],[-20.5,40.625],[53.125,-40.625]],"c":false}]}],"ix":2},"nm":"Path 1","mn":"ADBE Vector Shape - Group","hd":false},{"ty":"st","c":{"a":0,"k":[0.227450981736,0.647058844566,0.207843139768,1],"ix":3},"o":{"a":0,"k":100,"ix":4},"w":{"a":0,"k":27,"ix":5},"lc":2,"lj":2,"bm":0,"nm":"Stroke 1","mn":"ADBE Vector Graphic - Stroke","hd":false},{"ty":"tr","p":{"a":0,"k":[72.1,57.393],"ix":2},"a":{"a":0,"k":[0,0],"ix":1},"s":{"a":0,"k":[100,100],"ix":3},"r":{"a":0,"k":0,"ix":6},"o":{"a":0,"k":100,"ix":7},"sk":{"a":0,"k":0,"ix":4},"sa":{"a":0,"k":0,"ix":5},"nm":"Transform"}],"nm":"Group 1","np":2,"cix":2,"bm":0,"ix":1,"mn":"ADBE Vector Group","hd":false},{"ty":"tm","s":{"a":0,"k":0,"ix":1},"e":{"a":1,"k":[{"i":{"x":[0],"y":[1]},"o":{"x":[0.167],"y":[0.167]},"t":120,"s":[0]},{"t":147.310546875,"s":[100]}],"ix":2},"o":{"a":0,"k":0,"ix":3},"m":1,"ix":2,"nm":"Trim Paths 1","mn":"ADBE Vector Filter - Trim","hd":false}],"ip":120,"op":243,"st":-142,"bm":0},{"ddd":0,"ind":2,"ty":4,"nm":"tick Outlines","sr":1,"ks":{"o":{"a":0,"k":100,"ix":11},"r":{"a":0,"k":0,"ix":10},"p":{"a":0,"k":[1250,964.5,0],"ix":2,"l":2},"a":{"a":0,"k":[69.5,57,0],"ix":1,"l":2},"s":{"a":0,"k":[121,121,100],"ix":6,"l":2}},"ao":0,"shapes":[{"ty":"gr","it":[{"ind":0,"ty":"sh","ix":1,"ks":{"a":1,"k":[{"i":{"x":0.833,"y":0.833},"o":{"x":0.167,"y":0.167},"t":20,"s":[{"i":[[0,0],[0,0],[0,0]],"o":[[0,0],[0,0],[0,0]],"v":[[-53.125,9.625],[-20.5,40.625],[53.125,-40.625]],"c":false}]},{"i":{"x":0.833,"y":0.833},"o":{"x":0.167,"y":0.167},"t":22,"s":[{"i":[[0,0],[0,0],[0,0]],"o":[[0,0],[0,0],[0,0]],"v":[[-55.5,6.986],[-20.5,40.625],[53.125,-40.625]],"c":false}]},{"i":{"x":0.833,"y":0.833},"o":{"x":0.167,"y":0.167},"t":24,"s":[{"i":[[0,0],[0,0],[0,0]],"o":[[0,0],[0,0],[0,0]],"v":[[-57.772,4.462],[-20.5,40.625],[53.125,-40.625]],"c":false}]},{"i":{"x":0.833,"y":0.833},"o":{"x":0.167,"y":0.167},"t":25,"s":[{"i":[[0,0],[0,0],[0,0]],"o":[[0,0],[0,0],[0,0]],"v":[[-58.488,3.666],[-20.5,40.625],[53.125,-40.625]],"c":false}]},{"i":{"x":0.833,"y":0.833},"o":{"x":0.167,"y":0.167},"t":26,"s":[{"i":[[0,0],[0,0],[0,0]],"o":[[0,0],[0,0],[0,0]],"v":[[-59.204,2.871],[-20.5,40.625],[53.125,-40.625]],"c":false}]},{"i":{"x":0.833,"y":0.833},"o":{"x":0.167,"y":0.167},"t":27,"s":[{"i":[[0,0],[0,0],[0,0]],"o":[[0,0],[0,0],[0,0]],"v":[[-59.613,2.416],[-20.5,40.625],[53.125,-40.625]],"c":false}]},{"i":{"x":0.833,"y":0.833},"o":{"x":0.167,"y":0.167},"t":28,"s":[{"i":[[0,0],[0,0],[0,0]],"o":[[0,0],[0,0],[0,0]],"v":[[-60.022,1.962],[-20.5,40.625],[53.125,-40.625]],"c":false}]},{"i":{"x":0.833,"y":0.833},"o":{"x":0.167,"y":0.167},"t":29,"s":[{"i":[[0,0],[0,0],[0,0]],"o":[[0,0],[0,0],[0,0]],"v":[[-60.232,1.728],[-20.5,40.625],[53.125,-40.625]],"c":false}]},{"i":{"x":0.833,"y":0.833},"o":{"x":0.167,"y":0.167},"t":30,"s":[{"i":[[0,0],[0,0],[0,0]],"o":[[0,0],[0,0],[0,0]],"v":[[-60.442,1.495],[-20.5,40.625],[53.125,-40.625]],"c":false}]},{"i":{"x":0.833,"y":0.833},"o":{"x":0.167,"y":0.167},"t":31,"s":[{"i":[[0,0],[0,0],[0,0]],"o":[[0,0],[0,0],[0,0]],"v":[[-60.502,1.428],[-20.5,40.625],[53.125,-40.625]],"c":false}]},{"i":{"x":0.833,"y":0.833},"o":{"x":0.167,"y":0.167},"t":32,"s":[{"i":[[0,0],[0,0],[0,0]],"o":[[0,0],[0,0],[0,0]],"v":[[-60.563,1.361],[-20.5,40.625],[53.125,-40.625]],"c":false}]},{"i":{"x":0.833,"y":0.833},"o":{"x":0.167,"y":0.167},"t":33,"s":[{"i":[[0,0],[0,0],[0,0]],"o":[[0,0],[0,0],[0,0]],"v":[[-60.473,1.46],[-20.5,40.625],[53.125,-40.625]],"c":false}]},{"i":{"x":0.833,"y":0.833},"o":{"x":0.167,"y":0.167},"t":34,"s":[{"i":[[0,0],[0,0],[0,0]],"o":[[0,0],[0,0],[0,0]],"v":[[-60.384,1.56],[-20.5,40.625],[53.125,-40.625]],"c":false}]},{"i":{"x":0.833,"y":0.833},"o":{"x":0.167,"y":0.167},"t":35,"s":[{"i":[[0,0],[0,0],[0,0]],"o":[[0,0],[0,0],[0,0]],"v":[[-60.068,1.91],[-20.5,40.625],[53.125,-40.625]],"c":false}]},{"i":{"x":0.833,"y":0.833},"o":{"x":0.167,"y":0.167},"t":36,"s":[{"i":[[0,0],[0,0],[0,0]],"o":[[0,0],[0,0],[0,0]],"v":[[-59.753,2.26],[-20.5,40.625],[53.125,-40.625]],"c":false}]},{"i":{"x":0.833,"y":0.833},"o":{"x":0.167,"y":0.167},"t":37,"s":[{"i":[[0,0],[0,0],[0,0]],"o":[[0,0],[0,0],[0,0]],"v":[[-59.093,2.994],[-20.5,40.625],[53.125,-40.625]],"c":false}]},{"i":{"x":0.833,"y":0.833},"o":{"x":0.167,"y":0.167},"t":38,"s":[{"i":[[0,0],[0,0],[0,0]],"o":[[0,0],[0,0],[0,0]],"v":[[-58.433,3.727],[-20.5,40.625],[53.125,-40.625]],"c":false}]},{"i":{"x":0.833,"y":0.833},"o":{"x":0.167,"y":0.167},"t":40,"s":[{"i":[[0,0],[0,0],[0,0]],"o":[[0,0],[0,0],[0,0]],"v":[[-56.029,6.398],[-20.5,40.625],[53.125,-40.625]],"c":false}]},{"t":42,"s":[{"i":[[0,0],[0,0],[0,0]],"o":[[0,0],[0,0],[0,0]],"v":[[-53.125,9.625],[-20.5,40.625],[53.125,-40.625]],"c":false}]}],"ix":2},"nm":"Path 1","mn":"ADBE Vector Shape - Group","hd":false},{"ty":"st","c":{"a":0,"k":[0.227450981736,0.647058844566,0.207843139768,1],"ix":3},"o":{"a":0,"k":100,"ix":4},"w":{"a":0,"k":27,"ix":5},"lc":2,"lj":2,"bm":0,"nm":"Stroke 1","mn":"ADBE Vector Graphic - Stroke","hd":false},{"ty":"tr","p":{"a":0,"k":[72.1,57.393],"ix":2},"a":{"a":0,"k":[0,0],"ix":1},"s":{"a":0,"k":[100,100],"ix":3},"r":{"a":0,"k":0,"ix":6},"o":{"a":0,"k":100,"ix":7},"sk":{"a":0,"k":0,"ix":4},"sa":{"a":0,"k":0,"ix":5},"nm":"Transform"}],"nm":"Group 1","np":2,"cix":2,"bm":0,"ix":1,"mn":"ADBE Vector Group","hd":false},{"ty":"tm","s":{"a":0,"k":100,"ix":1},"e":{"a":1,"k":[{"i":{"x":[0.833],"y":[0.833]},"o":{"x":[0.167],"y":[0.167]},"t":42,"s":[0]},{"t":54,"s":[99]}],"ix":2},"o":{"a":0,"k":0,"ix":3},"m":1,"ix":2,"nm":"Trim Paths 1","mn":"ADBE Vector Filter - Trim","hd":false}],"ip":0,"op":54,"st":-130,"bm":0},{"ddd":0,"ind":3,"ty":4,"nm":"Shape Layer 4","parent":7,"sr":1,"ks":{"o":{"a":0,"k":100,"ix":11},"r":{"a":0,"k":208,"ix":10},"p":{"s":true,"x":{"a":1,"k":[{"i":{"x":[0.833],"y":[0.833]},"o":{"x":[0.167],"y":[0.167]},"t":100,"s":[-162.497]},{"t":120,"s":[-82.497]}],"ix":3},"y":{"a":1,"k":[{"i":{"x":[0.28],"y":[1]},"o":{"x":[0.167],"y":[0.167]},"t":100,"s":[-2.248]},{"i":{"x":[0.833],"y":[0.833]},"o":{"x":[0.72],"y":[0]},"t":110,"s":[-37.248]},{"t":120,"s":[0.752]}],"ix":4}},"a":{"a":0,"k":[0,0,0],"ix":1,"l":2},"s":{"a":0,"k":[172,172,100],"ix":6,"l":2}},"ao":0,"shapes":[{"d":3,"ty":"el","s":{"a":1,"k":[{"i":{"x":[0.833,0.833],"y":[0.833,0.833]},"o":{"x":[0.333,0.333],"y":[0,0]},"t":100,"s":[34,34]},{"t":120,"s":[21,21]}],"ix":2},"p":{"a":0,"k":[0,0],"ix":3},"nm":"Ellipse Path 1","mn":"ADBE Vector Shape - Ellipse","hd":false},{"ty":"fl","c":{"a":0,"k":[0.227450996637,0.647058844566,0.207843154669,1],"ix":4},"o":{"a":0,"k":100,"ix":5},"r":2,"bm":0,"nm":"Fill 2","mn":"ADBE Vector Graphic - Fill","hd":false},{"ty":"fl","c":{"a":0,"k":[0.227450996637,0.647058844566,0.207843154669,1],"ix":4},"o":{"a":0,"k":100,"ix":5},"r":2,"bm":0,"nm":"Fill 1","mn":"ADBE Vector Graphic - Fill","hd":false}],"ip":100,"op":121,"st":0,"bm":0},{"ddd":0,"ind":4,"ty":4,"nm":"Shape Layer 3","parent":7,"sr":1,"ks":{"o":{"a":0,"k":100,"ix":11},"r":{"a":1,"k":[{"i":{"x":[0.46],"y":[0.898]},"o":{"x":[0.55],"y":[0.149]},"t":76,"s":[5]},{"t":100,"s":[204]}],"ix":10},"p":{"s":true,"x":{"a":0,"k":0,"ix":3},"y":{"a":0,"k":0,"ix":4}},"a":{"a":0,"k":[-87.033,37.553,0],"ix":1,"l":2},"s":{"a":0,"k":[172,172,100],"ix":6,"l":2}},"ao":0,"shapes":[{"d":3,"ty":"el","s":{"a":0,"k":[34,34],"ix":2},"p":{"a":0,"k":[0,0],"ix":3},"nm":"Ellipse Path 1","mn":"ADBE Vector Shape - Ellipse","hd":false},{"ty":"fl","c":{"a":0,"k":[0.227450996637,0.647058844566,0.207843154669,1],"ix":4},"o":{"a":0,"k":100,"ix":5},"r":2,"bm":0,"nm":"Fill 2","mn":"ADBE Vector Graphic - Fill","hd":false},{"ty":"fl","c":{"a":0,"k":[0.227450996637,0.647058844566,0.207843154669,1],"ix":4},"o":{"a":0,"k":100,"ix":5},"r":2,"bm":0,"nm":"Fill 1","mn":"ADBE Vector Graphic - Fill","hd":false}],"ip":76,"op":101,"st":0,"bm":0},{"ddd":0,"ind":5,"ty":4,"nm":"Shape Layer 2","sr":1,"ks":{"o":{"a":0,"k":100,"ix":11},"r":{"a":0,"k":0,"ix":10},"p":{"s":true,"x":{"a":1,"k":[{"i":{"x":[0.833],"y":[0.833]},"o":{"x":[0.167],"y":[0.167]},"t":54,"s":[1317.428]},{"i":{"x":[0.833],"y":[0.833]},"o":{"x":[0.167],"y":[0.167]},"t":67,"s":[1360.314]},{"t":76,"s":[1390.428]}],"ix":3},"y":{"a":1,"k":[{"i":{"x":[0.28],"y":[1]},"o":{"x":[0.167],"y":[0.167]},"t":54,"s":[915.819]},{"i":{"x":[0.933],"y":[0.678]},"o":{"x":[0.596],"y":[0]},"t":64,"s":[885.819]},{"t":76,"s":[923.819]}],"ix":4}},"a":{"a":0,"k":[0,0,0],"ix":1,"l":2},"s":{"a":0,"k":[100,100,100],"ix":6,"l":2}},"ao":0,"shapes":[{"d":3,"ty":"el","s":{"a":1,"k":[{"i":{"x":[0.833,0.833],"y":[0.833,0.833]},"o":{"x":[0.167,0.167],"y":[0.167,0.167]},"t":54,"s":[35,35]},{"t":76,"s":[50,50]}],"ix":2},"p":{"a":0,"k":[0,0],"ix":3},"nm":"Ellipse Path 1","mn":"ADBE Vector Shape - Ellipse","hd":false},{"ty":"fl","c":{"a":0,"k":[0.227450996637,0.647058844566,0.207843154669,1],"ix":4},"o":{"a":0,"k":100,"ix":5},"r":2,"bm":0,"nm":"Fill 2","mn":"ADBE Vector Graphic - Fill","hd":false},{"ty":"fl","c":{"a":0,"k":[0.227450996637,0.647058844566,0.207843154669,1],"ix":4},"o":{"a":0,"k":100,"ix":5},"r":2,"bm":0,"nm":"Fill 1","mn":"ADBE Vector Graphic - Fill","hd":false}],"ip":54,"op":76,"st":0,"bm":0},{"ddd":0,"ind":6,"ty":4,"nm":"Sparkles","sr":1,"ks":{"o":{"a":0,"k":100,"ix":11},"r":{"a":0,"k":-18.161,"ix":10},"p":{"a":0,"k":[1458.133,822.426,0],"ix":2,"l":2},"a":{"a":0,"k":[722.269,341,0],"ix":1,"l":2},"s":{"a":0,"k":[172,172,100],"ix":6,"l":2}},"ao":0,"shapes":[{"ty":"gr","it":[{"ty":"gr","it":[{"ind":0,"ty":"sh","ix":1,"ks":{"a":0,"k":{"i":[[-5.181,-1.331],[0,-1.623],[1.571,-0.404],[4.559,-1.171],[1.313,-5.114],[1.331,-5.181],[1.623,0],[0.404,1.571],[1.171,4.559],[5.114,1.313],[5.181,1.331],[0,1.623],[-1.571,0.404],[-4.559,1.171],[-1.313,5.114],[-1.331,5.181],[-1.623,0],[-0.404,-1.571],[-1.171,-4.559],[-5.114,-1.313]],"o":[[1.571,0.404],[0,1.623],[-5.181,1.331],[-5.114,1.313],[-1.171,4.559],[-0.404,1.571],[-1.623,0],[-1.331,-5.181],[-1.313,-5.114],[-4.559,-1.171],[-1.571,-0.404],[0,-1.623],[5.181,-1.331],[5.114,-1.313],[1.171,-4.559],[0.404,-1.571],[1.623,0],[1.331,5.181],[1.313,5.114],[4.559,1.171]],"v":[[33.352,-3.443],[36.022,0],[33.352,3.443],[17.847,7.426],[7.426,17.847],[3.443,33.352],[0,36.022],[-3.443,33.352],[-7.426,17.847],[-17.847,7.426],[-33.352,3.443],[-36.022,0],[-33.352,-3.443],[-17.847,-7.426],[-7.426,-17.847],[-3.443,-33.352],[0,-36.022],[3.443,-33.352],[7.426,-17.847],[17.847,-7.426]],"c":true},"ix":2},"nm":"Path 1","mn":"ADBE Vector Shape - Group","hd":false},{"ty":"fl","c":{"a":0,"k":[1,1,1,1],"ix":4},"o":{"a":0,"k":100,"ix":5},"r":1,"bm":0,"nm":"Fill 1","mn":"ADBE Vector Graphic - Fill","hd":false},{"ty":"tr","p":{"a":0,"k":[59.491,62.796],"ix":2},"a":{"a":0,"k":[0,0],"ix":1},"s":{"a":0,"k":[100,100],"ix":3},"r":{"a":0,"k":0,"ix":6},"o":{"a":0,"k":100,"ix":7},"sk":{"a":0,"k":0,"ix":4},"sa":{"a":0,"k":0,"ix":5},"nm":"Transform"}],"nm":"Group 1","np":2,"cix":2,"bm":0,"ix":1,"mn":"ADBE Vector Group","hd":false},{"ty":"tr","p":{"a":1,"k":[{"i":{"x":0,"y":1},"o":{"x":0.167,"y":0.198},"t":114,"s":[540,384],"to":[0,0],"ti":[-25.961,-65.829]},{"t":170,"s":[744.1,412.487]}],"ix":2},"a":{"a":0,"k":[36.5,36.5],"ix":1},"s":{"a":1,"k":[{"i":{"x":[0.014,0.014],"y":[0.838,0.838]},"o":{"x":[0.18,0.18],"y":[0.434,0.434]},"t":114,"s":[-14.25,14.25]},{"t":170,"s":[-41.843,41.843]}],"ix":3},"r":{"a":1,"k":[{"i":{"x":[0],"y":[1]},"o":{"x":[0.167],"y":[0.167]},"t":114,"s":[-114.293]},{"t":170,"s":[-282.293]}],"ix":6},"o":{"a":1,"k":[{"i":{"x":[0.833],"y":[0.833]},"o":{"x":[0.167],"y":[0.167]},"t":148,"s":[100]},{"t":168,"s":[0]}],"ix":7},"sk":{"a":0,"k":0,"ix":4},"sa":{"a":0,"k":0,"ix":5},"nm":"Transform"}],"nm":"confetti star Outlines 5","np":1,"cix":2,"bm":0,"ix":1,"mn":"ADBE Vector Group","hd":false},{"ty":"gr","it":[{"ty":"gr","it":[{"ind":0,"ty":"sh","ix":1,"ks":{"a":0,"k":{"i":[[-5.181,-1.331],[0,-1.623],[1.571,-0.404],[4.559,-1.171],[1.313,-5.114],[1.331,-5.181],[1.623,0],[0.404,1.571],[1.171,4.559],[5.114,1.313],[5.181,1.331],[0,1.623],[-1.571,0.404],[-4.559,1.171],[-1.313,5.114],[-1.331,5.181],[-1.623,0],[-0.404,-1.571],[-1.171,-4.559],[-5.114,-1.313]],"o":[[1.571,0.404],[0,1.623],[-5.181,1.331],[-5.114,1.313],[-1.171,4.559],[-0.404,1.571],[-1.623,0],[-1.331,-5.181],[-1.313,-5.114],[-4.559,-1.171],[-1.571,-0.404],[0,-1.623],[5.181,-1.331],[5.114,-1.313],[1.171,-4.559],[0.404,-1.571],[1.623,0],[1.331,5.181],[1.313,5.114],[4.559,1.171]],"v":[[33.352,-3.443],[36.022,0],[33.352,3.443],[17.847,7.426],[7.426,17.847],[3.443,33.352],[0,36.022],[-3.443,33.352],[-7.426,17.847],[-17.847,7.426],[-33.352,3.443],[-36.022,0],[-33.352,-3.443],[-17.847,-7.426],[-7.426,-17.847],[-3.443,-33.352],[0,-36.022],[3.443,-33.352],[7.426,-17.847],[17.847,-7.426]],"c":true},"ix":2},"nm":"Path 1","mn":"ADBE Vector Shape - Group","hd":false},{"ty":"fl","c":{"a":0,"k":[1,1,1,1],"ix":4},"o":{"a":0,"k":100,"ix":5},"r":1,"bm":0,"nm":"Fill 1","mn":"ADBE Vector Graphic - Fill","hd":false},{"ty":"tr","p":{"a":0,"k":[36.022,36.978],"ix":2},"a":{"a":0,"k":[0,0],"ix":1},"s":{"a":0,"k":[100,100],"ix":3},"r":{"a":0,"k":0,"ix":6},"o":{"a":0,"k":100,"ix":7},"sk":{"a":0,"k":0,"ix":4},"sa":{"a":0,"k":0,"ix":5},"nm":"Transform"}],"nm":"Group 1","np":2,"cix":2,"bm":0,"ix":1,"mn":"ADBE Vector Group","hd":false},{"ty":"tr","p":{"a":1,"k":[{"i":{"x":0,"y":1},"o":{"x":0.167,"y":0.175},"t":110,"s":[540,384],"to":[0,0],"ti":[-124,6]},{"t":166,"s":[722,288]}],"ix":2},"a":{"a":0,"k":[36.5,36.5],"ix":1},"s":{"a":1,"k":[{"i":{"x":[0,0],"y":[1,1]},"o":{"x":[0.167,0.167],"y":[0.167,0.167]},"t":110,"s":[25,25]},{"t":166,"s":[73,73]}],"ix":3},"r":{"a":1,"k":[{"i":{"x":[0],"y":[1]},"o":{"x":[0.167],"y":[0.167]},"t":110,"s":[0]},{"t":166,"s":[168]}],"ix":6},"o":{"a":1,"k":[{"i":{"x":[0.833],"y":[0.833]},"o":{"x":[0.167],"y":[0.167]},"t":144,"s":[100]},{"t":164,"s":[0]}],"ix":7},"sk":{"a":0,"k":0,"ix":4},"sa":{"a":0,"k":0,"ix":5},"nm":"Transform"}],"nm":"confetti star Outlines 4","np":1,"cix":2,"bm":0,"ix":2,"mn":"ADBE Vector Group","hd":false}],"ip":124,"op":243,"st":78,"bm":0},{"ddd":0,"ind":7,"ty":4,"nm":"Shape Layer 1","sr":1,"ks":{"o":{"a":0,"k":100,"ix":11},"r":{"a":0,"k":0,"ix":10},"p":{"s":true,"x":{"a":1,"k":[{"i":{"x":[0.833],"y":[1]},"o":{"x":[0.167],"y":[0]},"t":76,"s":[1258]},{"t":100,"s":[1258]}],"ix":3},"y":{"a":1,"k":[{"i":{"x":[0.667],"y":[1]},"o":{"x":[0.51],"y":[0]},"t":76,"s":[965]},{"i":{"x":[0.49],"y":[1]},"o":{"x":[0.333],"y":[0]},"t":88,"s":[979]},{"t":100,"s":[965]}],"ix":4}},"a":{"a":0,"k":[0,0,0],"ix":1,"l":2},"s":{"a":1,"k":[{"i":{"x":[0.833,0.833,0.833],"y":[1,1,1]},"o":{"x":[0.167,0.167,0.167],"y":[0,0,0]},"t":0,"s":[105,105,100]},{"i":{"x":[0.833,0.833,0.833],"y":[1,1,1]},"o":{"x":[0.167,0.167,0.167],"y":[0,0,0]},"t":2,"s":[105,105,100]},{"i":{"x":[0.833,0.833,0.833],"y":[1,1,1]},"o":{"x":[0.167,0.167,0.167],"y":[0,0,0]},"t":4,"s":[105,105,100]},{"i":{"x":[0.833,0.833,0.833],"y":[1,1,1]},"o":{"x":[0.167,0.167,0.167],"y":[0,0,0]},"t":6,"s":[105,105,100]},{"i":{"x":[0.833,0.833,0.833],"y":[1,1,1]},"o":{"x":[0.167,0.167,0.167],"y":[0,0,0]},"t":8,"s":[105,105,100]},{"i":{"x":[0.833,0.833,0.833],"y":[1,1,1]},"o":{"x":[0.167,0.167,0.167],"y":[0,0,0]},"t":10,"s":[105,105,100]},{"i":{"x":[0.833,0.833,0.833],"y":[1,1,1]},"o":{"x":[0.167,0.167,0.167],"y":[0,0,0]},"t":12,"s":[105,105,100]},{"i":{"x":[0.833,0.833,0.833],"y":[1,1,1]},"o":{"x":[0.167,0.167,0.167],"y":[0,0,0]},"t":14,"s":[105,105,100]},{"i":{"x":[0.833,0.833,0.833],"y":[1,1,1]},"o":{"x":[0.167,0.167,0.167],"y":[0,0,0]},"t":16,"s":[105,105,100]},{"i":{"x":[0.833,0.833,0.833],"y":[1,1,1]},"o":{"x":[0.167,0.167,0.167],"y":[0,0,0]},"t":18,"s":[105,105,100]},{"i":{"x":[0.833,0.833,0.833],"y":[0.833,0.833,1]},"o":{"x":[0.167,0.167,0.167],"y":[0.167,0.167,0]},"t":20,"s":[105,105,100]},{"i":{"x":[0.833,0.833,0.833],"y":[0.833,0.833,1]},"o":{"x":[0.167,0.167,0.167],"y":[0.167,0.167,0]},"t":22,"s":[106.594,106.594,100]},{"i":{"x":[0.833,0.833,0.833],"y":[0.833,0.833,1]},"o":{"x":[0.167,0.167,0.167],"y":[0.167,0.167,0]},"t":24,"s":[108.13,108.13,100]},{"i":{"x":[0.833,0.833,0.833],"y":[0.833,0.833,1]},"o":{"x":[0.167,0.167,0.167],"y":[0.167,0.167,0]},"t":26,"s":[109.086,109.086,100]},{"i":{"x":[0.833,0.833,0.833],"y":[0.833,0.833,1]},"o":{"x":[0.167,0.167,0.167],"y":[0.167,0.167,0]},"t":28,"s":[109.64,109.64,100]},{"i":{"x":[0.833,0.833,0.833],"y":[0.833,0.833,1]},"o":{"x":[0.167,0.167,0.167],"y":[0.167,0.167,0]},"t":30,"s":[109.919,109.919,100]},{"i":{"x":[0.833,0.833,0.833],"y":[0.833,0.833,1]},"o":{"x":[0.167,0.167,0.167],"y":[0.167,0.167,0]},"t":32,"s":[110,110,100]},{"i":{"x":[0.833,0.833,0.833],"y":[0.833,0.833,1]},"o":{"x":[0.167,0.167,0.167],"y":[0.167,0.167,0]},"t":34,"s":[109.87,109.87,100]},{"i":{"x":[0.833,0.833,0.833],"y":[0.833,0.833,1]},"o":{"x":[0.167,0.167,0.167],"y":[0.167,0.167,0]},"t":36,"s":[109.369,109.369,100]},{"i":{"x":[0.833,0.833,0.833],"y":[0.833,0.833,1]},"o":{"x":[0.167,0.167,0.167],"y":[0.167,0.167,0]},"t":38,"s":[108.351,108.351,100]},{"i":{"x":[0.833,0.833,0.833],"y":[0.833,0.833,1]},"o":{"x":[0.167,0.167,0.167],"y":[0.167,0.167,0]},"t":40,"s":[106.548,106.548,100]},{"i":{"x":[0.833,0.833,0.833],"y":[0.833,0.833,1]},"o":{"x":[0.167,0.167,0.167],"y":[0.167,0.167,0]},"t":42,"s":[103.446,103.446,100]},{"i":{"x":[0.833,0.833,0.833],"y":[0.833,0.833,1]},"o":{"x":[0.167,0.167,0.167],"y":[0.167,0.167,0]},"t":44,"s":[98.26,98.26,100]},{"i":{"x":[0.833,0.833,0.833],"y":[0.833,0.833,1]},"o":{"x":[0.167,0.167,0.167],"y":[0.167,0.167,0]},"t":46,"s":[92.106,92.106,100]},{"i":{"x":[0.833,0.833,0.833],"y":[0.833,0.833,1]},"o":{"x":[0.167,0.167,0.167],"y":[0.167,0.167,0]},"t":48,"s":[88.144,88.144,100]},{"i":{"x":[0.833,0.833,0.833],"y":[0.833,0.833,1]},"o":{"x":[0.167,0.167,0.167],"y":[0.167,0.167,0]},"t":50,"s":[86.142,86.142,100]},{"i":{"x":[0.833,0.833,0.833],"y":[0.833,0.833,1]},"o":{"x":[0.167,0.167,0.167],"y":[0.167,0.167,0]},"t":52,"s":[85.241,85.241,100]},{"i":{"x":[0.833,0.833,0.833],"y":[0.833,0.833,1]},"o":{"x":[0.167,0.167,0.167],"y":[0.167,0.167,0]},"t":54,"s":[85,85,100]},{"i":{"x":[0.833,0.833,0.833],"y":[0.833,0.833,1]},"o":{"x":[0.167,0.167,0.167],"y":[0.167,0.167,0]},"t":56,"s":[84.955,84.955,100]},{"i":{"x":[0.833,0.833,0.833],"y":[1,1,1]},"o":{"x":[0.167,0.167,0.167],"y":[0,0,0]},"t":58,"s":[84.937,84.937,100]},{"i":{"x":[0.833,0.833,0.833],"y":[0.833,0.833,1]},"o":{"x":[0.167,0.167,0.167],"y":[0.167,0.167,0]},"t":60,"s":[84.937,84.937,100]},{"i":{"x":[0.833,0.833,0.833],"y":[0.833,0.833,1]},"o":{"x":[0.167,0.167,0.167],"y":[0.167,0.167,0]},"t":62,"s":[84.948,84.948,100]},{"i":{"x":[0.833,0.833,0.833],"y":[0.833,0.833,1]},"o":{"x":[0.167,0.167,0.167],"y":[0.167,0.167,0]},"t":64,"s":[84.963,84.963,100]},{"i":{"x":[0.833,0.833,0.833],"y":[0.833,0.833,1]},"o":{"x":[0.167,0.167,0.167],"y":[0.167,0.167,0]},"t":66,"s":[84.978,84.978,100]},{"i":{"x":[0.833,0.833,0.833],"y":[0.833,0.833,1]},"o":{"x":[0.167,0.167,0.167],"y":[0.167,0.167,0]},"t":68,"s":[84.99,84.99,100]},{"i":{"x":[0.833,0.833,0.833],"y":[0.833,0.833,1]},"o":{"x":[0.167,0.167,0.167],"y":[0.167,0.167,0]},"t":70,"s":[84.999,84.999,100]},{"i":{"x":[0.833,0.833,0.833],"y":[0.833,0.833,1]},"o":{"x":[0.167,0.167,0.167],"y":[0.167,0.167,0]},"t":72,"s":[85.004,85.004,100]},{"i":{"x":[0.833,0.833,0.833],"y":[0.833,0.833,1]},"o":{"x":[0.167,0.167,0.167],"y":[0.167,0.167,0]},"t":74,"s":[85.006,85.006,100]},{"i":{"x":[0.833,0.833,0.833],"y":[0.833,0.833,1]},"o":{"x":[0.167,0.167,0.167],"y":[0.167,0.167,0]},"t":76,"s":[85,85,100]},{"i":{"x":[0.833,0.833,0.833],"y":[0.833,0.833,1]},"o":{"x":[0.167,0.167,0.167],"y":[0.167,0.167,0]},"t":78,"s":[85.362,85.362,100]},{"i":{"x":[0.833,0.833,0.833],"y":[0.833,0.833,1]},"o":{"x":[0.167,0.167,0.167],"y":[0.167,0.167,0]},"t":80,"s":[86.589,86.589,100]},{"i":{"x":[0.833,0.833,0.833],"y":[0.833,0.833,1]},"o":{"x":[0.167,0.167,0.167],"y":[0.167,0.167,0]},"t":82,"s":[88.973,88.973,100]},{"i":{"x":[0.833,0.833,0.833],"y":[0.833,0.833,1]},"o":{"x":[0.167,0.167,0.167],"y":[0.167,0.167,0]},"t":84,"s":[92.955,92.955,100]},{"i":{"x":[0.833,0.833,0.833],"y":[0.833,0.833,1]},"o":{"x":[0.167,0.167,0.167],"y":[0.167,0.167,0]},"t":86,"s":[98.974,98.974,100]},{"i":{"x":[0.833,0.833,0.833],"y":[0.833,0.833,1]},"o":{"x":[0.167,0.167,0.167],"y":[0.167,0.167,0]},"t":88,"s":[105,105,100]},{"i":{"x":[0.833,0.833,0.833],"y":[0.833,0.833,1]},"o":{"x":[0.167,0.167,0.167],"y":[0.167,0.167,0]},"t":90,"s":[109.434,109.434,100]},{"i":{"x":[0.833,0.833,0.833],"y":[0.833,0.833,1]},"o":{"x":[0.167,0.167,0.167],"y":[0.167,0.167,0]},"t":92,"s":[111.193,111.193,100]},{"i":{"x":[0.833,0.833,0.833],"y":[0.833,0.833,1]},"o":{"x":[0.167,0.167,0.167],"y":[0.167,0.167,0]},"t":94,"s":[111.135,111.135,100]},{"i":{"x":[0.833,0.833,0.833],"y":[0.833,0.833,1]},"o":{"x":[0.167,0.167,0.167],"y":[0.167,0.167,0]},"t":96,"s":[110.056,110.056,100]},{"i":{"x":[0.833,0.833,0.833],"y":[0.833,0.833,1]},"o":{"x":[0.167,0.167,0.167],"y":[0.167,0.167,0]},"t":98,"s":[108.581,108.581,100]},{"i":{"x":[0.833,0.833,0.833],"y":[0.833,0.833,1]},"o":{"x":[0.167,0.167,0.167],"y":[0.167,0.167,0]},"t":100,"s":[107.133,107.133,100]},{"i":{"x":[0.833,0.833,0.833],"y":[0.833,0.833,1]},"o":{"x":[0.167,0.167,0.167],"y":[0.167,0.167,0]},"t":102,"s":[105.948,105.948,100]},{"i":{"x":[0.833,0.833,0.833],"y":[0.833,0.833,1]},"o":{"x":[0.167,0.167,0.167],"y":[0.167,0.167,0]},"t":104,"s":[105.114,105.114,100]},{"i":{"x":[0.833,0.833,0.833],"y":[0.833,0.833,1]},"o":{"x":[0.167,0.167,0.167],"y":[0.167,0.167,0]},"t":106,"s":[104.621,104.621,100]},{"i":{"x":[0.833,0.833,0.833],"y":[0.833,0.833,1]},"o":{"x":[0.167,0.167,0.167],"y":[0.167,0.167,0]},"t":108,"s":[104.406,104.406,100]},{"i":{"x":[0.833,0.833,0.833],"y":[0.833,0.833,1]},"o":{"x":[0.167,0.167,0.167],"y":[0.167,0.167,0]},"t":110,"s":[104.385,104.385,100]},{"i":{"x":[0.833,0.833,0.833],"y":[0.833,0.833,1]},"o":{"x":[0.167,0.167,0.167],"y":[0.167,0.167,0]},"t":112,"s":[104.478,104.478,100]},{"i":{"x":[0.833,0.833,0.833],"y":[0.833,0.833,1]},"o":{"x":[0.167,0.167,0.167],"y":[0.167,0.167,0]},"t":114,"s":[104.62,104.62,100]},{"i":{"x":[0.833,0.833,0.833],"y":[0.833,0.833,1]},"o":{"x":[0.167,0.167,0.167],"y":[0.167,0.167,0]},"t":116,"s":[104.766,104.766,100]},{"i":{"x":[0.833,0.833,0.833],"y":[0.833,0.833,1]},"o":{"x":[0.167,0.167,0.167],"y":[0.167,0.167,0]},"t":118,"s":[104.888,104.888,100]},{"i":{"x":[0.833,0.833,0.833],"y":[0.833,0.833,1]},"o":{"x":[0.167,0.167,0.167],"y":[0.167,0.167,0]},"t":120,"s":[104.977,104.977,100]},{"i":{"x":[0.833,0.833,0.833],"y":[0.833,0.833,1]},"o":{"x":[0.167,0.167,0.167],"y":[0.167,0.167,0]},"t":122,"s":[105.031,105.031,100]},{"i":{"x":[0.833,0.833,0.833],"y":[0.833,0.833,1]},"o":{"x":[0.167,0.167,0.167],"y":[0.167,0.167,0]},"t":124,"s":[105.056,105.056,100]},{"i":{"x":[0.833,0.833,0.833],"y":[0.833,0.833,1]},"o":{"x":[0.167,0.167,0.167],"y":[0.167,0.167,0]},"t":126,"s":[105.061,105.061,100]},{"i":{"x":[0.833,0.833,0.833],"y":[0.833,0.833,1]},"o":{"x":[0.167,0.167,0.167],"y":[0.167,0.167,0]},"t":128,"s":[105.054,105.054,100]},{"i":{"x":[0.833,0.833,0.833],"y":[0.833,0.833,1]},"o":{"x":[0.167,0.167,0.167],"y":[0.167,0.167,0]},"t":130,"s":[105.04,105.04,100]},{"i":{"x":[0.833,0.833,0.833],"y":[0.833,0.833,1]},"o":{"x":[0.167,0.167,0.167],"y":[0.167,0.167,0]},"t":132,"s":[105.026,105.026,100]},{"i":{"x":[0.833,0.833,0.833],"y":[0.833,0.833,1]},"o":{"x":[0.167,0.167,0.167],"y":[0.167,0.167,0]},"t":134,"s":[105.013,105.013,100]},{"i":{"x":[0.833,0.833,0.833],"y":[0.833,0.833,1]},"o":{"x":[0.167,0.167,0.167],"y":[0.167,0.167,0]},"t":136,"s":[105.004,105.004,100]},{"i":{"x":[0.833,0.833,0.833],"y":[0.833,0.833,1]},"o":{"x":[0.167,0.167,0.167],"y":[0.167,0.167,0]},"t":138,"s":[104.998,104.998,100]},{"i":{"x":[0.833,0.833,0.833],"y":[0.833,0.833,1]},"o":{"x":[0.167,0.167,0.167],"y":[0.167,0.167,0]},"t":140,"s":[104.995,104.995,100]},{"i":{"x":[0.833,0.833,0.833],"y":[0.833,0.833,1]},"o":{"x":[0.167,0.167,0.167],"y":[0.167,0.167,0]},"t":142,"s":[104.994,104.994,100]},{"i":{"x":[0.833,0.833,0.833],"y":[0.833,0.833,1]},"o":{"x":[0.167,0.167,0.167],"y":[0.167,0.167,0]},"t":144,"s":[104.995,104.995,100]},{"i":{"x":[0.833,0.833,0.833],"y":[0.833,0.833,1]},"o":{"x":[0.167,0.167,0.167],"y":[0.167,0.167,0]},"t":146,"s":[104.996,104.996,100]},{"i":{"x":[0.833,0.833,0.833],"y":[0.833,0.833,1]},"o":{"x":[0.167,0.167,0.167],"y":[0.167,0.167,0]},"t":148,"s":[104.997,104.997,100]},{"i":{"x":[0.833,0.833,0.833],"y":[1,1,1]},"o":{"x":[0.167,0.167,0.167],"y":[0,0,0]},"t":150,"s":[104.999,104.999,100]},{"i":{"x":[0.833,0.833,0.833],"y":[0.833,0.833,1]},"o":{"x":[0.167,0.167,0.167],"y":[0.167,0.167,0]},"t":152,"s":[104.999,104.999,100]},{"i":{"x":[0.833,0.833,0.833],"y":[1,1,1]},"o":{"x":[0.167,0.167,0.167],"y":[0,0,0]},"t":154,"s":[105,105,100]},{"i":{"x":[0.833,0.833,0.833],"y":[0.833,0.833,1]},"o":{"x":[0.167,0.167,0.167],"y":[0.167,0.167,0]},"t":156,"s":[105,105,100]},{"i":{"x":[0.833,0.833,0.833],"y":[1,1,1]},"o":{"x":[0.167,0.167,0.167],"y":[0,0,0]},"t":158,"s":[105.001,105.001,100]},{"i":{"x":[0.833,0.833,0.833],"y":[0.833,0.833,1]},"o":{"x":[0.167,0.167,0.167],"y":[0.167,0.167,0]},"t":160,"s":[105.001,105.001,100]},{"i":{"x":[0.833,0.833,0.833],"y":[1,1,1]},"o":{"x":[0.167,0.167,0.167],"y":[0,0,0]},"t":162,"s":[105,105,100]},{"i":{"x":[0.833,0.833,0.833],"y":[1,1,1]},"o":{"x":[0.167,0.167,0.167],"y":[0,0,0]},"t":164,"s":[105,105,100]},{"i":{"x":[0.833,0.833,0.833],"y":[1,1,1]},"o":{"x":[0.167,0.167,0.167],"y":[0,0,0]},"t":166,"s":[105,105,100]},{"i":{"x":[0.833,0.833,0.833],"y":[1,1,1]},"o":{"x":[0.167,0.167,0.167],"y":[0,0,0]},"t":168,"s":[105,105,100]},{"i":{"x":[0.833,0.833,0.833],"y":[1,1,1]},"o":{"x":[0.167,0.167,0.167],"y":[0,0,0]},"t":170,"s":[105,105,100]},{"i":{"x":[0.833,0.833,0.833],"y":[1,1,1]},"o":{"x":[0.167,0.167,0.167],"y":[0,0,0]},"t":172,"s":[105,105,100]},{"i":{"x":[0.833,0.833,0.833],"y":[1,1,1]},"o":{"x":[0.167,0.167,0.167],"y":[0,0,0]},"t":174,"s":[105,105,100]},{"i":{"x":[0.833,0.833,0.833],"y":[1,1,1]},"o":{"x":[0.167,0.167,0.167],"y":[0,0,0]},"t":176,"s":[105,105,100]},{"t":178,"s":[105,105,100]}],"ix":6,"l":2}},"ao":0,"shapes":[{"d":3,"ty":"el","s":{"a":0,"k":[388,388],"ix":2},"p":{"a":0,"k":[0,0],"ix":3},"nm":"Ellipse Path 1","mn":"ADBE Vector Shape - Ellipse","hd":false},{"ty":"fl","c":{"a":0,"k":[1,1,1,1],"ix":4},"o":{"a":0,"k":100,"ix":5},"r":2,"bm":0,"nm":"Fill 1","mn":"ADBE Vector Graphic - Fill","hd":false}],"ip":0,"op":243,"st":0,"bm":0}]}],"layers":[{"ddd":0,"ind":1,"ty":0,"nm":"Final EXPORT","refId":"comp_0","sr":1,"ks":{"o":{"a":0,"k":100,"ix":11},"r":{"a":0,"k":0,"ix":10},"p":{"a":0,"k":[215,215,0],"ix":2,"l":2},"a":{"a":0,"k":[471.5,215,0],"ix":1,"l":2},"s":{"a":0,"k":[100,100,100],"ix":6,"l":2}},"ao":0,"w":943,"h":430,"ip":0,"op":165,"st":0,"bm":0}],"markers":[]}