{
  "availableTrips": [
    {
      "id": 2000001848430144420,
      "idStr": "2000001848430144420",
      "travels": "Golden Metrolink",
      "vehicleType": "BUS",
      "busType": "A/C Semi Sleeper (2+2)",
      "busTypeId": 101,
      "operator": 16142,
      "serviceStartTime": "2024-04-05 23:00:00",
      "cancellationCalculationTimestamp": "Fri Apr 05 23:00:00 IST 2024",
      "routeId": 2000001800000144420,
      "rbRouteId": 18419639,
      "rbServiceId": "144420",
      "doj": "2024-04-05T00:00:00+05:30",
      "departureTime": 1380,
      "arrivalTime": 1620,
      "boardingTimes": [
        {
          "bpId": 244729,
          "bpName": "Swargate",
          "location": "Swargate",
          "time": 1380,
          "prime": true,
          "address": "Golden Metrolink  Travels, Near Natraj Hotel, Opp. Swargate ST Stand, Swargate, Pune",
          "contactNumber": " 7277127712 / 9393939472 ",
          "landmark": "Near Natraj Hotel, Opp. Swargate ST Stand, Swargate, Pune"
        }
      ],
      "droppingTimes": [
        {
          "bpId": 201702,
          "bpName": "Kalamboli",
          "location": "Kalamboli Mc Donolds Hotel",
          "time": 1560,
          "prime": false,
          "address": "Mc Donold Hotel, Sector 1E, Kalamboli, Navi Mumbai, Mumbai, Maharashtra 410218",
          "contactNumber": "9822550142 / 9393939472",
          "landmark": "Near Mc Donold Hotel"
        }

      ],
      "availableSeats": 17,
      "fares": [
        472.5
      ],
      "fareDetails": [
        {
          "baseFare": 450.0,
          "totalFare": 472.5,
          "serviceTaxPercentage": 5,
          "serviceTaxAbsolute": 22.5,
          "operatorServiceChargePercentage": 0,
          "operatorServiceChargeAbsolute": 0.0,
          "opFare": 0,
          "opGroupFare": 0,
          "markupFareAbsolute": 0,
          "markupFarePercentage": 0,
          "bookingFee": 0,
          "levyFare": 0,
          "srtFee": 0,
          "tollFee": 0,
          "childFare": 0,
          "bankT rexAmt": 0,
          "gst": 22.5,
          "serviceCharge": 0.0
        }
      ],
      "cancellationPolicy": "0:12:100:0;12:24:50:0;24:-1:10:0",
      "partialCancellationAllowed": true,
      "idProofRequired": false,
      "mTicketEnabled": true,
      "liveTrackingAvailable": false,
      "unAvailable": false,
      "zeroCancellationTime": 10.0,
      "cpId": 1,
      "source": 626,
      "destination": 649,
      "dropPointMandatory": false,
      "selfInventory": false,
      "bookable": true,
      "maxSeatsPerTicket": 6,
      "noSeatLayoutEnabled": false,
      "avlWindowSeats": -1,
      "busImageCount": -1,
      "rtc": false,
      "boCommission": 5.0,
      "partnerBaseCommission": 5.0,
      "gdsCommission": 0,
      "additionalCommission": 0,
      "busRoutes": "Pune-Mumbai",
      "agentServiceCharge": 0.0,
      "exactSearch": false,
      "duration": "4:00 hrs",
      "nextDay": false,
      "callFareBreakUpAPI": false,
      "imagesMetadataUrl": "/images/null",
      "boPriorityOperator": false,
      "offerPriceEnabled": false,
      "groupOfferPriceEnabled": false,
      "availableSingleSeat": 0,
      "ssagentAccount": false,
      "agentServiceChargeAllowed": true,
      "singleLadies": false,
      "ac": true,
      "nonAC": false,
      "seater": true,
      "sleeper": false,
      "vaccinatedBus": false,
      "vaccinatedStaff": false,
      "bpDpSeatLayout": false,
      "flatComApplicable": false,
      "happyHours": false,
      "primo": false,
      "busCancelled": false,
      "flatSSComApplicable": false,
      "availCatCard": false,
      "availSrCitizen": false,
      "primaryPaxCancellable": true,
      "otgEnabled": false,
      "AC": true,
      "isLMBAllowed": false
    },
    {
      "id": 2000001848430144330,
      "idStr": "2000001848430144330",
      "travels": "Golden Metrolink",
      "vehicleType": "BUS",
      "busType": "A/C Semi Sleeper (2+2)",
      "busTypeId": 101,
      "operator": 16142,
      "serviceStartTime": "2024-04-05 19:00:00",
      "cancellationCalculationTimestamp": "Fri Apr 05 19:00:00 IST 2024",
      "routeId": 2000001800000144330,
      "rbRouteId": 18314418,
      "rbServiceId": "144330",
      "doj": "2024-04-05T00:00:00+05:30",
      "departureTime": 1140,
      "arrivalTime": 1355,
      "boardingTimes": [
        {
          "bpId": 244729,
          "bpName": "Swargate",
          "location": "Swargate",
          "time": 1140,
          "prime": true,
          "address": "Golden Metrolink  Travels, Near Natraj Hotel, Opp. Swargate ST Stand, Swargate, Pune",
          "contactNumber": " 7277127712 / 9393939472 ",
          "landmark": "Near Natraj Hotel, Opp. Swargate ST Stand, Swargate, Pune"
        },
        {
          "bpId": 244722,
          "bpName": "Nal Stop",
          "location": "Nal Stop",
          "time": 1145,
          "prime": false,
          "address": "Hotel Samudra Restaurant Near Global Punjab\n917, Sharma Chambers, Karve Road, Opposite Matrix School, Nal Stop, Erandwane\nNal Stop, Pandurang Colony, Erandwane\nPune, Maharashtra 411004\nIndiaSumudra ",
          "contactNumber": " 7277127712 / 9850030666",
          "landmark": "Near Global Punjab And Samudra Restaurant."
        },
        {
          "bpId": 244730,
          "bpName": "More Vidyalay Bus Stop",
          "location": "Pushp Travels Kothrud",
          "time": 1150,
          "prime": false,
          "address": "Near Bank of Baroda ATM Sarsawati sedan Paud Rd, Mahaganesh Colony, Kothrud, Pune, Maharashtra 411038",
          "contactNumber": " 7277127712 / 9393939472 ",
          "landmark": "More Vidyalay Bus Stop"
        },
        {
          "bpId": 201669,
          "bpName": "Paud Road",
          "location": "Paud Road",
          "time": 1155,
          "prime": false,
          "address": "Vanaz Company, New Friends Society, Lokmanya Colony, Kothrud, Pune, 411038",
          "contactNumber": "7277127712 /  9850030666",
          "landmark": "Opp. Vanaz Company"
        },
        {
          "bpId": 201670,
          "bpName": "Bhusari Colony",
          "location": "Bhusari Colony",
          "time": 1160,
          "prime": false,
          "address": "NP Travels, Near Seven 11 Hotel  Bhusari Colony, Kothrud, Pune 411029 ",
          "contactNumber": "7277127712 / 9850030666",
          "landmark": "Seven 11 Restaurant Opp Royal Enfeild Showroom"
        },
        {
          "bpId": 201672,
          "bpName": "Chandini Chowk",
          "location": "Chandini Chowk",
          "time": 1170,
          "prime": false,
          "address": "Near ST Bus Stop, Pune-Mumbai Highway, Pune 411021",
          "contactNumber": "7277127712 / 9850030666",
          "landmark": "Near ST Bus Stop"
        },
        {
          "bpId": 201679,
          "bpName": "Baner",
          "location": "Baner",
          "time": 1180,
          "prime": false,
          "address": "Hotel orchid, Mahalunge Road, Radha Chowk, Baner, Pune, 411045",
          "contactNumber": "7277127712 /  9850030666",
          "landmark": "Near ORCHID Hotel"
        },
        {
          "bpId": 570373,
          "bpName": "Rajyog Hotel Hinjewadi",
          "location": "Hinje Wadi",
          "time": 1190,
          "prime": false,
          "address": "Hinjewadi Rajyog Hotel .Golden Metrolink\nNear Hinjewadi Bridge, Bhujbal chowk New Mumbai Banglore Highway.",
          "contactNumber": "7277127712 / 9850030666",
          "landmark": "Near Hotel Rajyog Garden."
        },
        {
          "bpI d": 201681,
          "bpName": "Wakad",
          "location": "Wakad",
          "time": 1200,
          "prime": false,
          "address": "Near Shani Mandir, MSRTC Bus Stop,Tathawade, Wakad, Pune 411033",
          "contactNumber": "7277127712 / 9850030666",
          "landmark": "Near Shani Mandir"
        },
        {
          "bpId": 244733,
          "bpName": "Talegaon Toll Plaza",
          "location": "Talegaon",
          "time": 1215,
          "prime": false,
          "address": "Talegaon Toll Plaza, Mumbai - Pune Expy, Urse, Maharashtra 410506\n",
          "contactNumber": " 7277127712 / 9850030666",
          "landmark": "Talegaon Toll Plaza"
        }
      ],
      "droppingTimes": [
        {
          "bpId": 201702,
          "bpName": "Kalamboli",
          "location": "Kalamboli Mc Donolds Hotel",
          "time": 1230,
          "prime": false,
          "address": "Mc Donold Hotel, Sector 1E, Kalamboli, Navi Mumbai, Mumbai, Maharashtra 410218",
          "contactNumber": "9822550142 / 9393939472",
          "landmark": "Near Mc Donold Hotel"
        },
        {
          "bpId": 201701,
          "bpName": "Kharghar",
          "location": "Kharghar",
          "time": 1300,
          "prime": false,
          "address": "L P Nerul bus  \n",
          "contactNumber": "9822550142 / 9393939472",
          "landmark": "L P Nerul flyover"
        },
        {
          "bpId": 201699,
          "bpName": "CBD Belapur ",
          "location": "CBD Belapur ",
          "time": 1305,
          "prime": false,
          "address": " CBD Belapur, Navi Mumbai, Maharashtra 400614 bridge ending towards pune",
          "contactNumber": "9822550142 / 9393939472",
          "landmark": "Bridge Ending Towards pune"
        },
        {
          "bpId": 201697,
          "bpName": "Nerul ",
          "location": "Nerul Lp",
          "time": 1310,
          "prime": false,
          "address": "Near L P Bus Stand, Sion - Panvel Expy, MIDC Industrial Area, Shiravane, Nerul, Navi Mumbai, 400706",
          "contactNumber": "9822550142 / 9393939472",
          "landmark": "Near L P Bus Stand"
        },
        {
          "bpId": 201696,
          "bpName": "Vashi",
          "location": "Vashi",
          "time": 1320,
          "prime": false,
          "address": "Vashi Plaza, Sion - Panvel Expy, Sector 17, Vashi, Navi Mumbai,  400703",
          "contactNumber": "9822550142 / 9393939472",
          "landmark": "Vashi Plaza"
        },
        {
          "bpId": 201694,
          "bpName": "Chembur",
          "location": "Chembur (E), Yogi Hotel",
          "time": 1335,
          "prime": false,
          "address": "Hotel Yogi Restaurant, yogi broadway, Chembur East, Mumbai,  400071",
          "contactNumber": "9822550142 / 9393939472",
          "landmark": "Near Hotel Yogi Restaurant"
        },
        {
          "bpId": 201693,
          "bpName": "Sion",
          "location": "Sion (E)",
          "time": 1345,
          "prime": false,
          "address": "Near Man Mandir Travels, Opp. Ashray Hotel, Road No.1, Near Railway Station, Sion West, Mumbai, 400022",
          "contactNumber": "9822550142 / 9393939472",
          "landmark": "Opp. Ashray Hotel"
        },
        {
          "bpId": 201692,
          "bpName": "Bandra East",
          "location": "Bandra (E) Kalanagar Bus Stop",
          "time": 1355,
          "prime": true,
          "address": "Kalanagar Bus Stop, Kherwadi, Bandra East, Mumbai,  400051",
          "contactNumber": "9822550142 / 9393939472",
          "landmark": "Kalanagar Bus Stop towards sion dharavi"
        },
        {
          "bpId": 201691,
          "bpName": "Santacruz East",
          "location": "Santacruz (E)",
          "time": 1360,
          "prime": false,
          "address": "M A Travels Vakola,  Santacruz East, Mumbai, 400055",
          "contactNumber": "9822550142 / 9393939472",
          "landmark": "Vakola Near M A Travels bridge ending Teacher colony bus stop"
        },
        {
          "bpId": 201690,
          "bpName": "Vile Parle East",
          "location": " Vile Parle (E) Centaur (Sahara) Hotel",
          "time": 1365,
          "prime": false,
          "address": "Jay Travels Domestic Airport Rd, Near Sahar Star Hotel  Vile Parle,(E) Mumbai,  400047",
          "contactNumber": "9393939472/  9822012306",
          "landmark": "Domestic Airport Rd Near Near Sahar Star Hotel"
        },
        {
          "bpId": 417962,
          "bpName": "Andheri East, Golden Metrolink Jay Travels",
          "location": "Andheri (E)  Bisleri",
          "time": 1367,
          "prime": false,
          "address": "Andheri (E)  Bisleri Stop  Golden Metrolink Jay Travels",
          "contactNumber": "9822550142 / 9393939472",
          "landmark": "Andheri (E)  Bisleri Stop  Golden Metrolink Jay Travels"
        },
        {
          "bpId": 201688,
          "bpName": "Jogeshwari East",
          "location": "Jogeshwari (E)",
          "time": 1370,
          "prime": false,
          "address": "Chembur,Maitri Park opp msrtc bus stop",
          "contactNumber": "9822550142 / 9393939472",
          "landmark": "R K studio"
        },
        {
          "bpId": 201687,
          "bpName": "Goregaon East",
          "location": "Goregaon East",
          "time": 1375,
          "prime": false,
          "address": "Karmarkar travels, Off Western Express Highway, Goregaon East, Goregaon East, Mumbai, 400063",
          "contactNumber": "9822550142 / 9393939472",
          "landmark": "Near Karmarkar travels, near  array flyover"
        },
        {
          "bpId": 201686,
          "bpName": "Malad East",
          "location": "Malad (E)",
          "time": 1380,
          "pri me": false,
          "address": "Shantaram talav Pushpa Park, Malad East, Mumbai, 400097",
          "contactNumber": "9822550142 / 9393939472",
          "landmark": "Omkar Building shantram talav malad"
        },
        {
          "bpId": 201685,
          "bpName": "Kandivali East",
          "location": "Kandivali  (E) Samta Nagar Police Station",
          "time": 1385,
          "prime": false,
          "address": "Samta Nagar Police Chowky, 5, Western Express Hwy, Jivdani Vikas Mandal, Akurli Nagar, Kandivali East, Mumbai 400101",
          "contactNumber": "9822550142 / 9393939472",
          "landmark": "Samta Nagar Police Chowky"
        },
        {
          "bpId": 201684,
          "bpName": "Borivali East",
          "location": "Borivali (E) National Park",
          "time": 1395,
          "prime": false,
          "address": "National Park, Near Axis Bank, Borivali East, Mumbai,  400066",
          "contactNumber": "9822012306 / 9393939472",
          "landmark": "National Park Near Axis Bank, Borivali East, Mumbai,  400066"
        }
      ],
      "availableSeats": 20,
      "fares": [
        472.5
      ],
      "fareDetails": [
        {
          "baseFare": 450.0,
          "totalFare": 472.5,
          "serviceTaxPercentage": 5,
          "serviceTaxAbsolute": 22.5,
          "operatorServiceChargePercentage": 0,
          "operatorServiceChargeAbsolute": 0.0,
          "opFare": 0,
          "opGroupFare": 0,
          "markupFareAbsolute": 0,
          "markupFarePercentage": 0,
          "bookingFee": 0,
          "levyFare": 0,
          "srtFee": 0,
          "tollFee": 0,
          "childFare": 0,
          "bankTrexAmt": 0,
          "gst": 22.5,
          "serviceCharge": 0.0
        }
      ],
      "cancellationPolicy": "0:12:100:0;12:24:50:0;24:-1:10:0",
      "partialCancellationAllowed": true,
      "idProofRequired": false,
      "mTicketEnabled": true,
      "liveTrackingAvailable": false,
      "unAvailable": false,
      "zeroCancellationTime": 10.0,
      "cpId": 1,
      "source": 626,
      "destination": 649,
      "dropPointMandatory": false,
      "selfInventory": false,
      "bookable": true,
      "maxSeatsPerTicket": 6,
      "noSeatLayoutEnabled": false,
      "avlWindowSeats": -1,
      "busImageCount": -1,
      "rtc": false,
      "boCommission": 5.0,
      "partnerBaseCommission": 5.0,
      "gdsCommission": 0,
      "additionalCommission": 0,
      "busRoutes": "Pune-Mumbai",
      "agentServiceCharge": 0.0,
      "exactSearch": false,
      "duration": "3:35 hrs",
      "nextDay": false,
      "callFareBreakUpAPI": false,
      "imagesMetadataUrl": "/images/null",
      "boPriorityOperator": false,
      "offerPriceEnabled": false,
      "groupOfferPriceEnabled": false,
      "availableSingleSeat": 0,
      "ssagentAccount": false,
      "agentServiceChargeAllowed": true,
      "singleLadies": false,
      "ac": true,
      "nonAC": false,
      "seater": true,
      "sleeper": false,
      "vaccinatedBus": false,
      "vaccinatedStaff": false,
      "bpDpSeatLayout": false,
      "flatComApplicable": false,
      "happyHours": false,
      "primo": false,
      "busCancelled": false,
      "flatSSComApplicable": false,
      "availCatCard": false,
      "availSrCitizen": false,
      "primaryPaxCancellable": true,
      "otgEnabled": false,
      "AC": true,
      "isLMBAllowed": false
    }
  ]
}